{
  "entrypoints": {
    "paymentStatistic": {
      "js": [
        "/build/runtime.d94b3b43.js",
        "/build/0.daf318dd.js",
        "/build/1.e0a91682.js",
        "/build/paymentStatistic.9feaf570.js"
      ]
    },
    "shopStatistic": {
      "js": [
        "/build/runtime.d94b3b43.js",
        "/build/0.daf318dd.js",
        "/build/1.e0a91682.js",
        "/build/shopStatistic.d48ede9c.js"
      ]
    },
    "app": {
      "js": [
        "/build/runtime.d94b3b43.js",
        "/build/0.daf318dd.js",
        "/build/3.02a722a1.js",
        "/build/app.a646e401.js"
      ]
    },
    "main-base": {
      "js": [
        "/build/runtime.d94b3b43.js"
      ],
      "css": [
        "/build/main-base.4e64a21c.css"
      ]
    },
    "navbar-base": {
      "js": [
        "/build/runtime.d94b3b43.js"
      ],
      "css": [
        "/build/navbar-base.575726f7.css"
      ]
    }
  }
}